README.md
setup.py
pulumi_aws_quickstart_vpc/__init__.py
pulumi_aws_quickstart_vpc/_inputs.py
pulumi_aws_quickstart_vpc/_utilities.py
pulumi_aws_quickstart_vpc/provider.py
pulumi_aws_quickstart_vpc/pulumi-plugin.json
pulumi_aws_quickstart_vpc/py.typed
pulumi_aws_quickstart_vpc/vpc.py
pulumi_aws_quickstart_vpc.egg-info/PKG-INFO
pulumi_aws_quickstart_vpc.egg-info/SOURCES.txt
pulumi_aws_quickstart_vpc.egg-info/dependency_links.txt
pulumi_aws_quickstart_vpc.egg-info/not-zip-safe
pulumi_aws_quickstart_vpc.egg-info/requires.txt
pulumi_aws_quickstart_vpc.egg-info/top_level.txt