Metadata-Version: 2.1
Name: pulumi-aws-quickstart-vpc
Version: 0.0.5
Summary: UNKNOWN
Home-page: UNKNOWN
License: UNKNOWN
Platform: UNKNOWN
Requires-Python: >=3.7
